pyksurlquery/__init__.py
pyksurlquery/extDB.py
pyksurlquery/mmatch.py
pyksurlquery/settings.py
pyksurlquery/udmurl.py
pyksurlquery/urltype_def.py
pyksurlquery-2.0.3.dist-info/METADATA
pyksurlquery-2.0.3.dist-info/WHEEL
pyksurlquery-2.0.3.dist-info/top_level.txt
pyksurlquery-2.0.3.dist-info/RECORD
