Metadata-Version: 2.1
Name: pyksurlquery
Version: 2.0.3
Summary: url query module
Home-page: UNKNOWN
Author: UNKNOWN
Author-email: UNKNOWN
License: UNKNOWN
Platform: UNKNOWN
Requires-Dist: chardet (==3.0.4)
Requires-Dist: requests (==2.11.1)
Requires-Dist: urllib3 (==1.26.6)
